{
  "hash": "ed8a9969",
  "configHash": "7557e3a9",
  "lockfileHash": "52f44399",
  "browserHash": "ba7939b2",
  "optimized": {
    "vue": {
      "src": "../../../../../../node_modules/vue/dist/vue.runtime.esm-bundler.js",
      "file": "vue.js",
      "fileHash": "b58717ed",
      "needsInterop": false
    },
    "vitepress > @vue/devtools-api": {
      "src": "../../../../../../node_modules/@vue/devtools-api/dist/index.js",
      "file": "vitepress___@vue_devtools-api.js",
      "fileHash": "400aab3f",
      "needsInterop": false
    },
    "vitepress > @vueuse/core": {
      "src": "../../../../../../node_modules/@vueuse/core/index.mjs",
      "file": "vitepress___@vueuse_core.js",
      "fileHash": "cc9a9466",
      "needsInterop": false
    },
    "@theme/index": {
      "src": "../../../../../../node_modules/vitepress/dist/client/theme-default/index.js",
      "file": "@theme_index.js",
      "fileHash": "cfe1f370",
      "needsInterop": false
    }
  },
  "chunks": {
    "chunk-7YAD3VRR": {
      "file": "chunk-7YAD3VRR.js"
    },
    "chunk-BKML3YCO": {
      "file": "chunk-BKML3YCO.js"
    }
  }
}